lumber/__init__.py
lumber/settings.py
lumber/version.py
lumber/base/__init__.py
lumber/config/__init__.py
lumber/hub/__init__.py
lumber/tools/__init__.py
lumber_sdk-1.1.1.dist-info/LICENSE
lumber_sdk-1.1.1.dist-info/METADATA
lumber_sdk-1.1.1.dist-info/WHEEL
lumber_sdk-1.1.1.dist-info/top_level.txt
lumber_sdk-1.1.1.dist-info/RECORD
