Metadata-Version: 2.1
Name: lumber-sdk
Version: 1.1.1
Summary: An open-source Python SDK for connecting to the LumberHub platform
Home-page: https://github.com/hivecv/lumber-sdk
Author: HiveCV
Author-email: lukasz@hivecv.com
Keywords: data aggregation device configuration open source development kit
Classifier: Development Status :: 3 - Alpha
Classifier: Intended Audience :: Developers
Classifier: Programming Language :: Python :: 3
Classifier: Programming Language :: Python :: 3.7
Classifier: Programming Language :: Python :: 3.8
Classifier: Programming Language :: Python :: 3.9
Classifier: License :: OSI Approved :: MIT License
Classifier: Operating System :: OS Independent
Requires-Python: >=3.7
License-File: LICENSE
Requires-Dist: requests
Requires-Dist: jsonschema
